odoo/addons/sale_pricelist_packaging/README.rst
odoo/addons/sale_pricelist_packaging/__init__.py
odoo/addons/sale_pricelist_packaging/__manifest__.py
odoo/addons/sale_pricelist_packaging/i18n/sale_pricelist_packaging.pot
odoo/addons/sale_pricelist_packaging/models/__init__.py
odoo/addons/sale_pricelist_packaging/models/product_pricelist.py
odoo/addons/sale_pricelist_packaging/models/sale_order.py
odoo/addons/sale_pricelist_packaging/readme/CONTRIBUTORS.md
odoo/addons/sale_pricelist_packaging/readme/DESCRIPTION.md
odoo/addons/sale_pricelist_packaging/static/description/icon.png
odoo/addons/sale_pricelist_packaging/static/description/index.html
odoo/addons/sale_pricelist_packaging/tests/__init__.py
odoo/addons/sale_pricelist_packaging/tests/test_pricelist.py
odoo/addons/sale_pricelist_packaging/views/product_pricelist.xml
odoo_addon_sale_pricelist_packaging-18.0.1.0.0.2.dist-info/METADATA
odoo_addon_sale_pricelist_packaging-18.0.1.0.0.2.dist-info/WHEEL
odoo_addon_sale_pricelist_packaging-18.0.1.0.0.2.dist-info/top_level.txt
odoo_addon_sale_pricelist_packaging-18.0.1.0.0.2.dist-info/RECORD
